{"tilesPos":[{"x":107,"y":-16},{"x":108,"y":-16},{"x":109,"y":-16},{"x":110,"y":-16},{"x":111,"y":-16},{"x":112,"y":-16},{"x":113,"y":-16},{"x":114,"y":-16},{"x":115,"y":-16},{"x":116,"y":-16},{"x":117,"y":-16},{"x":118,"y":-16},{"x":119,"y":-16},{"x":120,"y":-16},{"x":121,"y":-16},{"x":122,"y":-16},{"x":123,"y":-16},{"x":124,"y":-16},{"x":125,"y":-16},{"x":107,"y":-15},{"x":110,"y":-15},{"x":113,"y":-15},{"x":116,"y":-15},{"x":119,"y":-15},{"x":122,"y":-15},{"x":125,"y":-15},{"x":107,"y":-14},{"x":110,"y":-14},{"x":113,"y":-14},{"x":116,"y":-14},{"x":119,"y":-14},{"x":122,"y":-14},{"x":125,"y":-14},{"x":107,"y":-13},{"x":110,"y":-13},{"x":113,"y":-13},{"x":116,"y":-13},{"x":119,"y":-13},{"x":122,"y":-13},{"x":125,"y":-13},{"x":107,"y":-12},{"x":110,"y":-12},{"x":113,"y":-12},{"x":116,"y":-12},{"x":119,"y":-12},{"x":122,"y":-12},{"x":125,"y":-12},{"x":107,"y":-11},{"x":110,"y":-11},{"x":113,"y":-11},{"x":116,"y":-11},{"x":119,"y":-11},{"x":122,"y":-11},{"x":125,"y":-11},{"x":107,"y":-10},{"x":110,"y":-10},{"x":113,"y":-10},{"x":116,"y":-10},{"x":119,"y":-10},{"x":122,"y":-10},{"x":125,"y":-10},{"x":107,"y":-9},{"x":110,"y":-9},{"x":113,"y":-9},{"x":116,"y":-9},{"x":119,"y":-9},{"x":122,"y":-9},{"x":125,"y":-9},{"x":107,"y":-8},{"x":110,"y":-8},{"x":113,"y":-8},{"x":116,"y":-8},{"x":119,"y":-8},{"x":122,"y":-8},{"x":125,"y":-8},{"x":17,"y":-7},{"x":18,"y":-7},{"x":19,"y":-7},{"x":20,"y":-7},{"x":21,"y":-7},{"x":22,"y":-7},{"x":23,"y":-7},{"x":107,"y":-7},{"x":110,"y":-7},{"x":113,"y":-7},{"x":116,"y":-7},{"x":119,"y":-7},{"x":122,"y":-7},{"x":125,"y":-7},{"x":13,"y":-6},{"x":14,"y":-6},{"x":15,"y":-6},{"x":16,"y":-6},{"x":17,"y":-6},{"x":18,"y":-6},{"x":19,"y":-6},{"x":20,"y":-6},{"x":21,"y":-6},{"x":22,"y":-6},{"x":23,"y":-6},{"x":24,"y":-6},{"x":25,"y":-6},{"x":107,"y":-6},{"x":110,"y":-6},{"x":113,"y":-6},{"x":116,"y":-6},{"x":119,"y":-6},{"x":122,"y":-6},{"x":125,"y":-6},{"x":13,"y":-5},{"x":14,"y":-5},{"x":15,"y":-5},{"x":16,"y":-5},{"x":17,"y":-5},{"x":18,"y":-5},{"x":19,"y":-5},{"x":20,"y":-5},{"x":21,"y":-5},{"x":22,"y":-5},{"x":23,"y":-5},{"x":24,"y":-5},{"x":25,"y":-5},{"x":26,"y":-5},{"x":27,"y":-5},{"x":80,"y":-5},{"x":81,"y":-5},{"x":82,"y":-5},{"x":107,"y":-5},{"x":110,"y":-5},{"x":113,"y":-5},{"x":116,"y":-5},{"x":119,"y":-5},{"x":122,"y":-5},{"x":125,"y":-5},{"x":-18,"y":-4},{"x":-17,"y":-4},{"x":-16,"y":-4},{"x":-12,"y":-4},{"x":-11,"y":-4},{"x":-10,"y":-4},{"x":-9,"y":-4},{"x":-8,"y":-4},{"x":-7,"y":-4},{"x":-6,"y":-4},{"x":-5,"y":-4},{"x":-4,"y":-4},{"x":-3,"y":-4},{"x":-2,"y":-4},{"x":3,"y":-4},{"x":4,"y":-4},{"x":5,"y":-4},{"x":6,"y":-4},{"x":7,"y":-4},{"x":10,"y":-4},{"x":11,"y":-4},{"x":12,"y":-4},{"x":13,"y":-4},{"x":14,"y":-4},{"x":15,"y":-4},{"x":16,"y":-4},{"x":17,"y":-4},{"x":18,"y":-4},{"x":19,"y":-4},{"x":20,"y":-4},{"x":21,"y":-4},{"x":22,"y":-4},{"x":23,"y":-4},{"x":24,"y":-4},{"x":25,"y":-4},{"x":26,"y":-4},{"x":27,"y":-4},{"x":28,"y":-4},{"x":29,"y":-4},{"x":72,"y":-4},{"x":73,"y":-4},{"x":76,"y":-4},{"x":77,"y":-4},{"x":78,"y":-4},{"x":79,"y":-4},{"x":80,"y":-4},{"x":81,"y":-4},{"x":82,"y":-4},{"x":83,"y":-4},{"x":84,"y":-4},{"x":107,"y":-4},{"x":110,"y":-4},{"x":113,"y":-4},{"x":116,"y":-4},{"x":119,"y":-4},{"x":122,"y":-4},{"x":125,"y":-4},{"x":-18,"y":-3},{"x":-17,"y":-3},{"x":-12,"y":-3},{"x":-11,"y":-3},{"x":-10,"y":-3},{"x":-9,"y":-3},{"x":-8,"y":-3},{"x":-7,"y":-3},{"x":-6,"y":-3},{"x":-5,"y":-3},{"x":-4,"y":-3},{"x":-3,"y":-3},{"x":-2,"y":-3},{"x":4,"y":-3},{"x":5,"y":-3},{"x":6,"y":-3},{"x":7,"y":-3},{"x":8,"y":-3},{"x":9,"y":-3},{"x":10,"y":-3},{"x":11,"y":-3},{"x":12,"y":-3},{"x":13,"y":-3},{"x":14,"y":-3},{"x":15,"y":-3},{"x":16,"y":-3},{"x":17,"y":-3},{"x":18,"y":-3},{"x":19,"y":-3},{"x":20,"y":-3},{"x":21,"y":-3},{"x":22,"y":-3},{"x":23,"y":-3},{"x":24,"y":-3},{"x":25,"y":-3},{"x":26,"y":-3},{"x":27,"y":-3},{"x":28,"y":-3},{"x":29,"y":-3},{"x":68,"y":-3},{"x":69,"y":-3},{"x":70,"y":-3},{"x":71,"y":-3},{"x":72,"y":-3},{"x":73,"y":-3},{"x":74,"y":-3},{"x":75,"y":-3},{"x":76,"y":-3},{"x":77,"y":-3},{"x":78,"y":-3},{"x":79,"y":-3},{"x":80,"y":-3},{"x":81,"y":-3},{"x":82,"y":-3},{"x":83,"y":-3},{"x":84,"y":-3},{"x":85,"y":-3},{"x":86,"y":-3},{"x":87,"y":-3},{"x":88,"y":-3},{"x":89,"y":-3},{"x":90,"y":-3},{"x":91,"y":-3},{"x":92,"y":-3},{"x":93,"y":-3},{"x":107,"y":-3},{"x":110,"y":-3},{"x":113,"y":-3},{"x":116,"y":-3},{"x":119,"y":-3},{"x":122,"y":-3},{"x":125,"y":-3},{"x":-19,"y":-2},{"x":-18,"y":-2},{"x":-17,"y":-2},{"x":-8,"y":-2},{"x":-7,"y":-2},{"x":-6,"y":-2},{"x":-5,"y":-2},{"x":-4,"y":-2},{"x":-3,"y":-2},{"x":-2,"y":-2},{"x":6,"y":-2},{"x":7,"y":-2},{"x":8,"y":-2},{"x":9,"y":-2},{"x":10,"y":-2},{"x":11,"y":-2},{"x":27,"y":-2},{"x":28,"y":-2},{"x":29,"y":-2},{"x":32,"y":-2},{"x":33,"y":-2},{"x":34,"y":-2},{"x":35,"y":-2},{"x":36,"y":-2},{"x":37,"y":-2},{"x":65,"y":-2},{"x":66,"y":-2},{"x":67,"y":-2},{"x":68,"y":-2},{"x":69,"y":-2},{"x":70,"y":-2},{"x":71,"y":-2},{"x":72,"y":-2},{"x":73,"y":-2},{"x":74,"y":-2},{"x":75,"y":-2},{"x":76,"y":-2},{"x":77,"y":-2},{"x":78,"y":-2},{"x":79,"y":-2},{"x":80,"y":-2},{"x":81,"y":-2},{"x":82,"y":-2},{"x":83,"y":-2},{"x":84,"y":-2},{"x":85,"y":-2},{"x":86,"y":-2},{"x":87,"y":-2},{"x":88,"y":-2},{"x":89,"y":-2},{"x":90,"y":-2},{"x":91,"y":-2},{"x":92,"y":-2},{"x":93,"y":-2},{"x":107,"y":-2},{"x":110,"y":-2},{"x":113,"y":-2},{"x":116,"y":-2},{"x":119,"y":-2},{"x":122,"y":-2},{"x":125,"y":-2},{"x":-20,"y":-1},{"x":-19,"y":-1},{"x":-18,"y":-1},{"x":-17,"y":-1},{"x":7,"y":-1},{"x":8,"y":-1},{"x":9,"y":-1},{"x":10,"y":-1},{"x":11,"y":-1},{"x":32,"y":-1},{"x":33,"y":-1},{"x":34,"y":-1},{"x":35,"y":-1},{"x":36,"y":-1},{"x":37,"y":-1},{"x":40,"y":-1},{"x":41,"y":-1},{"x":42,"y":-1},{"x":64,"y":-1},{"x":65,"y":-1},{"x":66,"y":-1},{"x":67,"y":-1},{"x":68,"y":-1},{"x":69,"y":-1},{"x":70,"y":-1},{"x":71,"y":-1},{"x":72,"y":-1},{"x":73,"y":-1},{"x":74,"y":-1},{"x":75,"y":-1},{"x":76,"y":-1},{"x":77,"y":-1},{"x":78,"y":-1},{"x":79,"y":-1},{"x":80,"y":-1},{"x":81,"y":-1},{"x":82,"y":-1},{"x":83,"y":-1},{"x":84,"y":-1},{"x":85,"y":-1},{"x":86,"y":-1},{"x":87,"y":-1},{"x":88,"y":-1},{"x":89,"y":-1},{"x":90,"y":-1},{"x":91,"y":-1},{"x":92,"y":-1},{"x":93,"y":-1},{"x":94,"y":-1},{"x":107,"y":-1},{"x":110,"y":-1},{"x":113,"y":-1},{"x":116,"y":-1},{"x":119,"y":-1},{"x":122,"y":-1},{"x":125,"y":-1},{"x":-20,"y":0},{"x":-19,"y":0},{"x":-18,"y":0},{"x":-17,"y":0},{"x":32,"y":0},{"x":33,"y":0},{"x":34,"y":0},{"x":35,"y":0},{"x":40,"y":0},{"x":41,"y":0},{"x":42,"y":0},{"x":90,"y":0},{"x":91,"y":0},{"x":92,"y":0},{"x":93,"y":0},{"x":94,"y":0},{"x":107,"y":0},{"x":110,"y":0},{"x":113,"y":0},{"x":116,"y":0},{"x":119,"y":0},{"x":122,"y":0},{"x":125,"y":0},{"x":-20,"y":1},{"x":-19,"y":1},{"x":-18,"y":1},{"x":-17,"y":1},{"x":26,"y":1},{"x":27,"y":1},{"x":28,"y":1},{"x":29,"y":1},{"x":34,"y":1},{"x":35,"y":1},{"x":90,"y":1},{"x":91,"y":1},{"x":92,"y":1},{"x":93,"y":1},{"x":94,"y":1},{"x":107,"y":1},{"x":108,"y":1},{"x":109,"y":1},{"x":110,"y":1},{"x":111,"y":1},{"x":112,"y":1},{"x":113,"y":1},{"x":114,"y":1},{"x":115,"y":1},{"x":116,"y":1},{"x":117,"y":1},{"x":118,"y":1},{"x":119,"y":1},{"x":120,"y":1},{"x":121,"y":1},{"x":122,"y":1},{"x":123,"y":1},{"x":124,"y":1},{"x":125,"y":1},{"x":-20,"y":2},{"x":-19,"y":2},{"x":-18,"y":2},{"x":-17,"y":2},{"x":9,"y":2},{"x":10,"y":2},{"x":11,"y":2},{"x":12,"y":2},{"x":13,"y":2},{"x":14,"y":2},{"x":15,"y":2},{"x":16,"y":2},{"x":17,"y":2},{"x":18,"y":2},{"x":19,"y":2},{"x":20,"y":2},{"x":21,"y":2},{"x":22,"y":2},{"x":23,"y":2},{"x":24,"y":2},{"x":25,"y":2},{"x":26,"y":2},{"x":27,"y":2},{"x":28,"y":2},{"x":34,"y":2},{"x":35,"y":2},{"x":90,"y":2},{"x":91,"y":2},{"x":92,"y":2},{"x":93,"y":2},{"x":94,"y":2},{"x":-19,"y":3},{"x":-18,"y":3},{"x":-17,"y":3},{"x":9,"y":3},{"x":10,"y":3},{"x":11,"y":3},{"x":12,"y":3},{"x":13,"y":3},{"x":14,"y":3},{"x":15,"y":3},{"x":16,"y":3},{"x":17,"y":3},{"x":18,"y":3},{"x":19,"y":3},{"x":20,"y":3},{"x":21,"y":3},{"x":22,"y":3},{"x":23,"y":3},{"x":24,"y":3},{"x":25,"y":3},{"x":26,"y":3},{"x":33,"y":3},{"x":34,"y":3},{"x":35,"y":3},{"x":36,"y":3},{"x":37,"y":3},{"x":45,"y":3},{"x":46,"y":3},{"x":47,"y":3},{"x":48,"y":3},{"x":49,"y":3},{"x":50,"y":3},{"x":51,"y":3},{"x":52,"y":3},{"x":90,"y":3},{"x":91,"y":3},{"x":92,"y":3},{"x":93,"y":3},{"x":-19,"y":4},{"x":-18,"y":4},{"x":-17,"y":4},{"x":-16,"y":4},{"x":9,"y":4},{"x":10,"y":4},{"x":11,"y":4},{"x":12,"y":4},{"x":13,"y":4},{"x":24,"y":4},{"x":25,"y":4},{"x":26,"y":4},{"x":31,"y":4},{"x":32,"y":4},{"x":33,"y":4},{"x":34,"y":4},{"x":35,"y":4},{"x":36,"y":4},{"x":37,"y":4},{"x":38,"y":4},{"x":46,"y":4},{"x":47,"y":4},{"x":48,"y":4},{"x":49,"y":4},{"x":50,"y":4},{"x":51,"y":4},{"x":52,"y":4},{"x":53,"y":4},{"x":54,"y":4},{"x":90,"y":4},{"x":91,"y":4},{"x":92,"y":4},{"x":93,"y":4},{"x":105,"y":4},{"x":106,"y":4},{"x":108,"y":4},{"x":109,"y":4},{"x":110,"y":4},{"x":111,"y":4},{"x":112,"y":4},{"x":113,"y":4},{"x":114,"y":4},{"x":115,"y":4},{"x":116,"y":4},{"x":117,"y":4},{"x":118,"y":4},{"x":119,"y":4},{"x":120,"y":4},{"x":121,"y":4},{"x":122,"y":4},{"x":123,"y":4},{"x":124,"y":4},{"x":125,"y":4},{"x":135,"y":4},{"x":136,"y":4},{"x":137,"y":4},{"x":138,"y":4},{"x":139,"y":4},{"x":140,"y":4},{"x":141,"y":4},{"x":-18,"y":5},{"x":-17,"y":5},{"x":-16,"y":5},{"x":-15,"y":5},{"x":-14,"y":5},{"x":-13,"y":5},{"x":24,"y":5},{"x":25,"y":5},{"x":26,"y":5},{"x":49,"y":5},{"x":50,"y":5},{"x":51,"y":5},{"x":52,"y":5},{"x":53,"y":5},{"x":54,"y":5},{"x":65,"y":5},{"x":66,"y":5},{"x":67,"y":5},{"x":68,"y":5},{"x":69,"y":5},{"x":70,"y":5},{"x":71,"y":5},{"x":72,"y":5},{"x":73,"y":5},{"x":74,"y":5},{"x":75,"y":5},{"x":76,"y":5},{"x":77,"y":5},{"x":78,"y":5},{"x":79,"y":5},{"x":80,"y":5},{"x":81,"y":5},{"x":82,"y":5},{"x":83,"y":5},{"x":84,"y":5},{"x":85,"y":5},{"x":86,"y":5},{"x":90,"y":5},{"x":91,"y":5},{"x":92,"y":5},{"x":93,"y":5},{"x":94,"y":5},{"x":105,"y":5},{"x":106,"y":5},{"x":107,"y":5},{"x":108,"y":5},{"x":109,"y":5},{"x":110,"y":5},{"x":111,"y":5},{"x":112,"y":5},{"x":113,"y":5},{"x":114,"y":5},{"x":115,"y":5},{"x":116,"y":5},{"x":117,"y":5},{"x":118,"y":5},{"x":119,"y":5},{"x":120,"y":5},{"x":121,"y":5},{"x":122,"y":5},{"x":123,"y":5},{"x":124,"y":5},{"x":125,"y":5},{"x":126,"y":5},{"x":129,"y":5},{"x":130,"y":5},{"x":131,"y":5},{"x":132,"y":5},{"x":133,"y":5},{"x":134,"y":5},{"x":135,"y":5},{"x":136,"y":5},{"x":137,"y":5},{"x":138,"y":5},{"x":139,"y":5},{"x":140,"y":5},{"x":141,"y":5},{"x":142,"y":5},{"x":143,"y":5},{"x":-18,"y":6},{"x":-17,"y":6},{"x":-16,"y":6},{"x":-15,"y":6},{"x":-14,"y":6},{"x":-13,"y":6},{"x":-12,"y":6},{"x":-11,"y":6},{"x":-10,"y":6},{"x":-5,"y":6},{"x":-4,"y":6},{"x":-3,"y":6},{"x":-2,"y":6},{"x":16,"y":6},{"x":17,"y":6},{"x":18,"y":6},{"x":19,"y":6},{"x":24,"y":6},{"x":25,"y":6},{"x":26,"y":6},{"x":27,"y":6},{"x":53,"y":6},{"x":54,"y":6},{"x":55,"y":6},{"x":56,"y":6},{"x":65,"y":6},{"x":66,"y":6},{"x":67,"y":6},{"x":68,"y":6},{"x":69,"y":6},{"x":70,"y":6},{"x":71,"y":6},{"x":72,"y":6},{"x":73,"y":6},{"x":74,"y":6},{"x":75,"y":6},{"x":76,"y":6},{"x":77,"y":6},{"x":78,"y":6},{"x":79,"y":6},{"x":80,"y":6},{"x":81,"y":6},{"x":82,"y":6},{"x":83,"y":6},{"x":84,"y":6},{"x":85,"y":6},{"x":86,"y":6},{"x":90,"y":6},{"x":91,"y":6},{"x":92,"y":6},{"x":93,"y":6},{"x":94,"y":6},{"x":95,"y":6},{"x":96,"y":6},{"x":97,"y":6},{"x":98,"y":6},{"x":99,"y":6},{"x":100,"y":6},{"x":101,"y":6},{"x":104,"y":6},{"x":105,"y":6},{"x":106,"y":6},{"x":107,"y":6},{"x":108,"y":6},{"x":109,"y":6},{"x":110,"y":6},{"x":111,"y":6},{"x":112,"y":6},{"x":113,"y":6},{"x":114,"y":6},{"x":115,"y":6},{"x":116,"y":6},{"x":117,"y":6},{"x":118,"y":6},{"x":119,"y":6},{"x":120,"y":6},{"x":121,"y":6},{"x":122,"y":6},{"x":123,"y":6},{"x":124,"y":6},{"x":125,"y":6},{"x":126,"y":6},{"x":127,"y":6},{"x":128,"y":6},{"x":129,"y":6},{"x":130,"y":6},{"x":131,"y":6},{"x":132,"y":6},{"x":133,"y":6},{"x":134,"y":6},{"x":135,"y":6},{"x":136,"y":6},{"x":139,"y":6},{"x":140,"y":6},{"x":141,"y":6},{"x":142,"y":6},{"x":143,"y":6},{"x":144,"y":6},{"x":145,"y":6},{"x":-16,"y":7},{"x":-15,"y":7},{"x":-14,"y":7},{"x":-13,"y":7},{"x":-12,"y":7},{"x":-11,"y":7},{"x":-10,"y":7},{"x":-9,"y":7},{"x":-8,"y":7},{"x":-7,"y":7},{"x":-6,"y":7},{"x":-5,"y":7},{"x":-4,"y":7},{"x":-3,"y":7},{"x":-2,"y":7},{"x":-1,"y":7},{"x":0,"y":7},{"x":1,"y":7},{"x":2,"y":7},{"x":3,"y":7},{"x":8,"y":7},{"x":9,"y":7},{"x":10,"y":7},{"x":11,"y":7},{"x":12,"y":7},{"x":13,"y":7},{"x":14,"y":7},{"x":15,"y":7},{"x":16,"y":7},{"x":17,"y":7},{"x":18,"y":7},{"x":19,"y":7},{"x":20,"y":7},{"x":25,"y":7},{"x":26,"y":7},{"x":27,"y":7},{"x":28,"y":7},{"x":35,"y":7},{"x":54,"y":7},{"x":55,"y":7},{"x":56,"y":7},{"x":57,"y":7},{"x":65,"y":7},{"x":66,"y":7},{"x":67,"y":7},{"x":68,"y":7},{"x":69,"y":7},{"x":70,"y":7},{"x":71,"y":7},{"x":72,"y":7},{"x":73,"y":7},{"x":74,"y":7},{"x":75,"y":7},{"x":76,"y":7},{"x":77,"y":7},{"x":78,"y":7},{"x":79,"y":7},{"x":80,"y":7},{"x":81,"y":7},{"x":82,"y":7},{"x":83,"y":7},{"x":84,"y":7},{"x":85,"y":7},{"x":86,"y":7},{"x":90,"y":7},{"x":91,"y":7},{"x":92,"y":7},{"x":93,"y":7},{"x":94,"y":7},{"x":95,"y":7},{"x":96,"y":7},{"x":97,"y":7},{"x":98,"y":7},{"x":99,"y":7},{"x":100,"y":7},{"x":101,"y":7},{"x":102,"y":7},{"x":103,"y":7},{"x":104,"y":7},{"x":105,"y":7},{"x":106,"y":7},{"x":113,"y":7},{"x":118,"y":7},{"x":125,"y":7},{"x":126,"y":7},{"x":127,"y":7},{"x":128,"y":7},{"x":129,"y":7},{"x":130,"y":7},{"x":132,"y":7},{"x":134,"y":7},{"x":135,"y":7},{"x":140,"y":7},{"x":141,"y":7},{"x":142,"y":7},{"x":143,"y":7},{"x":144,"y":7},{"x":145,"y":7},{"x":146,"y":7},{"x":147,"y":7},{"x":148,"y":7},{"x":151,"y":7},{"x":152,"y":7},{"x":153,"y":7},{"x":154,"y":7},{"x":155,"y":7},{"x":-12,"y":8},{"x":-11,"y":8},{"x":-10,"y":8},{"x":-9,"y":8},{"x":-8,"y":8},{"x":-7,"y":8},{"x":-6,"y":8},{"x":-5,"y":8},{"x":-4,"y":8},{"x":-3,"y":8},{"x":-2,"y":8},{"x":-1,"y":8},{"x":0,"y":8},{"x":1,"y":8},{"x":2,"y":8},{"x":3,"y":8},{"x":4,"y":8},{"x":5,"y":8},{"x":6,"y":8},{"x":7,"y":8},{"x":8,"y":8},{"x":9,"y":8},{"x":10,"y":8},{"x":11,"y":8},{"x":12,"y":8},{"x":13,"y":8},{"x":14,"y":8},{"x":15,"y":8},{"x":16,"y":8},{"x":17,"y":8},{"x":18,"y":8},{"x":19,"y":8},{"x":20,"y":8},{"x":21,"y":8},{"x":27,"y":8},{"x":28,"y":8},{"x":29,"y":8},{"x":30,"y":8},{"x":31,"y":8},{"x":35,"y":8},{"x":40,"y":8},{"x":41,"y":8},{"x":42,"y":8},{"x":43,"y":8},{"x":44,"y":8},{"x":45,"y":8},{"x":46,"y":8},{"x":47,"y":8},{"x":56,"y":8},{"x":57,"y":8},{"x":58,"y":8},{"x":59,"y":8},{"x":60,"y":8},{"x":65,"y":8},{"x":66,"y":8},{"x":67,"y":8},{"x":68,"y":8},{"x":70,"y":8},{"x":71,"y":8},{"x":72,"y":8},{"x":73,"y":8},{"x":74,"y":8},{"x":75,"y":8},{"x":76,"y":8},{"x":77,"y":8},{"x":78,"y":8},{"x":79,"y":8},{"x":80,"y":8},{"x":81,"y":8},{"x":82,"y":8},{"x":83,"y":8},{"x":84,"y":8},{"x":85,"y":8},{"x":86,"y":8},{"x":91,"y":8},{"x":92,"y":8},{"x":93,"y":8},{"x":94,"y":8},{"x":95,"y":8},{"x":96,"y":8},{"x":97,"y":8},{"x":98,"y":8},{"x":99,"y":8},{"x":100,"y":8},{"x":101,"y":8},{"x":102,"y":8},{"x":103,"y":8},{"x":104,"y":8},{"x":105,"y":8},{"x":106,"y":8},{"x":125,"y":8},{"x":126,"y":8},{"x":127,"y":8},{"x":128,"y":8},{"x":130,"y":8},{"x":135,"y":8},{"x":140,"y":8},{"x":141,"y":8},{"x":142,"y":8},{"x":143,"y":8},{"x":144,"y":8},{"x":145,"y":8},{"x":146,"y":8},{"x":147,"y":8},{"x":148,"y":8},{"x":149,"y":8},{"x":150,"y":8},{"x":151,"y":8},{"x":152,"y":8},{"x":153,"y":8},{"x":154,"y":8},{"x":155,"y":8},{"x":156,"y":8},{"x":157,"y":8},{"x":-9,"y":9},{"x":-8,"y":9},{"x":-7,"y":9},{"x":-6,"y":9},{"x":-5,"y":9},{"x":-4,"y":9},{"x":-3,"y":9},{"x":-2,"y":9},{"x":-1,"y":9},{"x":0,"y":9},{"x":1,"y":9},{"x":2,"y":9},{"x":3,"y":9},{"x":4,"y":9},{"x":5,"y":9},{"x":6,"y":9},{"x":7,"y":9},{"x":8,"y":9},{"x":9,"y":9},{"x":10,"y":9},{"x":11,"y":9},{"x":12,"y":9},{"x":13,"y":9},{"x":14,"y":9},{"x":15,"y":9},{"x":16,"y":9},{"x":17,"y":9},{"x":18,"y":9},{"x":19,"y":9},{"x":20,"y":9},{"x":21,"y":9},{"x":22,"y":9},{"x":23,"y":9},{"x":30,"y":9},{"x":31,"y":9},{"x":32,"y":9},{"x":33,"y":9},{"x":34,"y":9},{"x":35,"y":9},{"x":36,"y":9},{"x":37,"y":9},{"x":38,"y":9},{"x":39,"y":9},{"x":40,"y":9},{"x":41,"y":9},{"x":42,"y":9},{"x":43,"y":9},{"x":44,"y":9},{"x":45,"y":9},{"x":46,"y":9},{"x":47,"y":9},{"x":57,"y":9},{"x":58,"y":9},{"x":59,"y":9},{"x":60,"y":9},{"x":61,"y":9},{"x":65,"y":9},{"x":66,"y":9},{"x":67,"y":9},{"x":68,"y":9},{"x":71,"y":9},{"x":72,"y":9},{"x":73,"y":9},{"x":74,"y":9},{"x":75,"y":9},{"x":76,"y":9},{"x":77,"y":9},{"x":78,"y":9},{"x":79,"y":9},{"x":80,"y":9},{"x":81,"y":9},{"x":82,"y":9},{"x":83,"y":9},{"x":84,"y":9},{"x":85,"y":9},{"x":86,"y":9},{"x":93,"y":9},{"x":94,"y":9},{"x":95,"y":9},{"x":96,"y":9},{"x":97,"y":9},{"x":98,"y":9},{"x":99,"y":9},{"x":100,"y":9},{"x":101,"y":9},{"x":102,"y":9},{"x":103,"y":9},{"x":104,"y":9},{"x":105,"y":9},{"x":106,"y":9},{"x":125,"y":9},{"x":126,"y":9},{"x":127,"y":9},{"x":128,"y":9},{"x":137,"y":9},{"x":140,"y":9},{"x":141,"y":9},{"x":142,"y":9},{"x":143,"y":9},{"x":144,"y":9},{"x":145,"y":9},{"x":146,"y":9},{"x":147,"y":9},{"x":148,"y":9},{"x":149,"y":9},{"x":150,"y":9},{"x":151,"y":9},{"x":152,"y":9},{"x":153,"y":9},{"x":154,"y":9},{"x":155,"y":9},{"x":156,"y":9},{"x":157,"y":9},{"x":158,"y":9},{"x":-1,"y":10},{"x":0,"y":10},{"x":1,"y":10},{"x":2,"y":10},{"x":3,"y":10},{"x":4,"y":10},{"x":5,"y":10},{"x":6,"y":10},{"x":7,"y":10},{"x":8,"y":10},{"x":9,"y":10},{"x":10,"y":10},{"x":11,"y":10},{"x":12,"y":10},{"x":13,"y":10},{"x":14,"y":10},{"x":19,"y":10},{"x":20,"y":10},{"x":21,"y":10},{"x":22,"y":10},{"x":23,"y":10},{"x":24,"y":10},{"x":25,"y":10},{"x":65,"y":10},{"x":66,"y":10},{"x":67,"y":10},{"x":68,"y":10},{"x":71,"y":10},{"x":72,"y":10},{"x":73,"y":10},{"x":74,"y":10},{"x":75,"y":10},{"x":76,"y":10},{"x":77,"y":10},{"x":81,"y":10},{"x":82,"y":10},{"x":83,"y":10},{"x":86,"y":10},{"x":96,"y":10},{"x":97,"y":10},{"x":98,"y":10},{"x":99,"y":10},{"x":100,"y":10},{"x":101,"y":10},{"x":102,"y":10},{"x":103,"y":10},{"x":104,"y":10},{"x":105,"y":10},{"x":106,"y":10},{"x":126,"y":10},{"x":127,"y":10},{"x":137,"y":10},{"x":140,"y":10},{"x":141,"y":10},{"x":142,"y":10},{"x":143,"y":10},{"x":144,"y":10},{"x":145,"y":10},{"x":146,"y":10},{"x":147,"y":10},{"x":148,"y":10},{"x":149,"y":10},{"x":150,"y":10},{"x":151,"y":10},{"x":152,"y":10},{"x":153,"y":10},{"x":154,"y":10},{"x":155,"y":10},{"x":156,"y":10},{"x":157,"y":10},{"x":158,"y":10},{"x":159,"y":10},{"x":3,"y":11},{"x":4,"y":11},{"x":5,"y":11},{"x":6,"y":11},{"x":7,"y":11},{"x":9,"y":11},{"x":10,"y":11},{"x":22,"y":11},{"x":23,"y":11},{"x":24,"y":11},{"x":25,"y":11},{"x":26,"y":11},{"x":27,"y":11},{"x":28,"y":11},{"x":29,"y":11},{"x":30,"y":11},{"x":31,"y":11},{"x":32,"y":11},{"x":33,"y":11},{"x":34,"y":11},{"x":35,"y":11},{"x":36,"y":11},{"x":37,"y":11},{"x":38,"y":11},{"x":39,"y":11},{"x":40,"y":11},{"x":41,"y":11},{"x":42,"y":11},{"x":43,"y":11},{"x":44,"y":11},{"x":45,"y":11},{"x":46,"y":11},{"x":47,"y":11},{"x":48,"y":11},{"x":65,"y":11},{"x":66,"y":11},{"x":67,"y":11},{"x":72,"y":11},{"x":73,"y":11},{"x":74,"y":11},{"x":75,"y":11},{"x":82,"y":11},{"x":98,"y":11},{"x":99,"y":11},{"x":100,"y":11},{"x":101,"y":11},{"x":102,"y":11},{"x":103,"y":11},{"x":104,"y":11},{"x":105,"y":11},{"x":106,"y":11},{"x":110,"y":11},{"x":112,"y":11},{"x":113,"y":11},{"x":115,"y":11},{"x":116,"y":11},{"x":118,"y":11},{"x":119,"y":11},{"x":121,"y":11},{"x":122,"y":11},{"x":132,"y":11},{"x":140,"y":11},{"x":143,"y":11},{"x":144,"y":11},{"x":145,"y":11},{"x":146,"y":11},{"x":153,"y":11},{"x":154,"y":11},{"x":158,"y":11},{"x":159,"y":11},{"x":160,"y":11},{"x":22,"y":12},{"x":23,"y":12},{"x":24,"y":12},{"x":25,"y":12},{"x":26,"y":12},{"x":27,"y":12},{"x":28,"y":12},{"x":29,"y":12},{"x":30,"y":12},{"x":31,"y":12},{"x":32,"y":12},{"x":33,"y":12},{"x":34,"y":12},{"x":35,"y":12},{"x":36,"y":12},{"x":37,"y":12},{"x":38,"y":12},{"x":39,"y":12},{"x":40,"y":12},{"x":41,"y":12},{"x":42,"y":12},{"x":43,"y":12},{"x":44,"y":12},{"x":45,"y":12},{"x":46,"y":12},{"x":47,"y":12},{"x":48,"y":12},{"x":49,"y":12},{"x":65,"y":12},{"x":66,"y":12},{"x":67,"y":12},{"x":68,"y":12},{"x":73,"y":12},{"x":74,"y":12},{"x":75,"y":12},{"x":88,"y":12},{"x":89,"y":12},{"x":90,"y":12},{"x":91,"y":12},{"x":92,"y":12},{"x":93,"y":12},{"x":99,"y":12},{"x":100,"y":12},{"x":101,"y":12},{"x":102,"y":12},{"x":103,"y":12},{"x":104,"y":12},{"x":105,"y":12},{"x":106,"y":12},{"x":107,"y":12},{"x":109,"y":12},{"x":110,"y":12},{"x":112,"y":12},{"x":113,"y":12},{"x":115,"y":12},{"x":116,"y":12},{"x":118,"y":12},{"x":119,"y":12},{"x":121,"y":12},{"x":122,"y":12},{"x":123,"y":12},{"x":135,"y":12},{"x":158,"y":12},{"x":159,"y":12},{"x":160,"y":12},{"x":26,"y":13},{"x":27,"y":13},{"x":28,"y":13},{"x":29,"y":13},{"x":30,"y":13},{"x":31,"y":13},{"x":32,"y":13},{"x":33,"y":13},{"x":34,"y":13},{"x":35,"y":13},{"x":36,"y":13},{"x":37,"y":13},{"x":38,"y":13},{"x":39,"y":13},{"x":40,"y":13},{"x":41,"y":13},{"x":42,"y":13},{"x":43,"y":13},{"x":44,"y":13},{"x":45,"y":13},{"x":46,"y":13},{"x":47,"y":13},{"x":48,"y":13},{"x":49,"y":13},{"x":50,"y":13},{"x":51,"y":13},{"x":64,"y":13},{"x":65,"y":13},{"x":66,"y":13},{"x":67,"y":13},{"x":68,"y":13},{"x":73,"y":13},{"x":74,"y":13},{"x":75,"y":13},{"x":79,"y":13},{"x":80,"y":13},{"x":83,"y":13},{"x":84,"y":13},{"x":85,"y":13},{"x":86,"y":13},{"x":100,"y":13},{"x":101,"y":13},{"x":102,"y":13},{"x":103,"y":13},{"x":104,"y":13},{"x":105,"y":13},{"x":106,"y":13},{"x":107,"y":13},{"x":109,"y":13},{"x":110,"y":13},{"x":112,"y":13},{"x":113,"y":13},{"x":115,"y":13},{"x":116,"y":13},{"x":118,"y":13},{"x":119,"y":13},{"x":121,"y":13},{"x":122,"y":13},{"x":123,"y":13},{"x":124,"y":13},{"x":158,"y":13},{"x":159,"y":13},{"x":160,"y":13},{"x":34,"y":14},{"x":35,"y":14},{"x":36,"y":14},{"x":37,"y":14},{"x":38,"y":14},{"x":39,"y":14},{"x":40,"y":14},{"x":41,"y":14},{"x":44,"y":14},{"x":45,"y":14},{"x":46,"y":14},{"x":47,"y":14},{"x":48,"y":14},{"x":49,"y":14},{"x":50,"y":14},{"x":51,"y":14},{"x":52,"y":14},{"x":53,"y":14},{"x":54,"y":14},{"x":62,"y":14},{"x":63,"y":14},{"x":64,"y":14},{"x":65,"y":14},{"x":66,"y":14},{"x":67,"y":14},{"x":68,"y":14},{"x":79,"y":14},{"x":80,"y":14},{"x":85,"y":14},{"x":86,"y":14},{"x":87,"y":14},{"x":101,"y":14},{"x":102,"y":14},{"x":103,"y":14},{"x":104,"y":14},{"x":105,"y":14},{"x":106,"y":14},{"x":107,"y":14},{"x":109,"y":14},{"x":110,"y":14},{"x":112,"y":14},{"x":113,"y":14},{"x":115,"y":14},{"x":116,"y":14},{"x":118,"y":14},{"x":119,"y":14},{"x":121,"y":14},{"x":122,"y":14},{"x":123,"y":14},{"x":124,"y":14},{"x":130,"y":14},{"x":131,"y":14},{"x":132,"y":14},{"x":133,"y":14},{"x":158,"y":14},{"x":159,"y":14},{"x":160,"y":14},{"x":38,"y":15},{"x":39,"y":15},{"x":46,"y":15},{"x":47,"y":15},{"x":48,"y":15},{"x":49,"y":15},{"x":50,"y":15},{"x":51,"y":15},{"x":52,"y":15},{"x":53,"y":15},{"x":54,"y":15},{"x":55,"y":15},{"x":56,"y":15},{"x":57,"y":15},{"x":58,"y":15},{"x":59,"y":15},{"x":60,"y":15},{"x":61,"y":15},{"x":62,"y":15},{"x":63,"y":15},{"x":64,"y":15},{"x":65,"y":15},{"x":66,"y":15},{"x":67,"y":15},{"x":68,"y":15},{"x":69,"y":15},{"x":80,"y":15},{"x":85,"y":15},{"x":86,"y":15},{"x":87,"y":15},{"x":88,"y":15},{"x":102,"y":15},{"x":103,"y":15},{"x":104,"y":15},{"x":105,"y":15},{"x":106,"y":15},{"x":107,"y":15},{"x":109,"y":15},{"x":110,"y":15},{"x":112,"y":15},{"x":113,"y":15},{"x":115,"y":15},{"x":116,"y":15},{"x":118,"y":15},{"x":119,"y":15},{"x":121,"y":15},{"x":122,"y":15},{"x":123,"y":15},{"x":124,"y":15},{"x":125,"y":15},{"x":130,"y":15},{"x":131,"y":15},{"x":132,"y":15},{"x":157,"y":15},{"x":158,"y":15},{"x":159,"y":15},{"x":160,"y":15},{"x":47,"y":16},{"x":48,"y":16},{"x":49,"y":16},{"x":50,"y":16},{"x":51,"y":16},{"x":52,"y":16},{"x":53,"y":16},{"x":54,"y":16},{"x":55,"y":16},{"x":56,"y":16},{"x":57,"y":16},{"x":58,"y":16},{"x":59,"y":16},{"x":60,"y":16},{"x":61,"y":16},{"x":62,"y":16},{"x":63,"y":16},{"x":64,"y":16},{"x":65,"y":16},{"x":66,"y":16},{"x":67,"y":16},{"x":68,"y":16},{"x":69,"y":16},{"x":70,"y":16},{"x":71,"y":16},{"x":73,"y":16},{"x":74,"y":16},{"x":85,"y":16},{"x":86,"y":16},{"x":87,"y":16},{"x":88,"y":16},{"x":91,"y":16},{"x":92,"y":16},{"x":93,"y":16},{"x":94,"y":16},{"x":95,"y":16},{"x":96,"y":16},{"x":97,"y":16},{"x":103,"y":16},{"x":104,"y":16},{"x":105,"y":16},{"x":106,"y":16},{"x":107,"y":16},{"x":109,"y":16},{"x":110,"y":16},{"x":112,"y":16},{"x":113,"y":16},{"x":115,"y":16},{"x":116,"y":16},{"x":118,"y":16},{"x":119,"y":16},{"x":121,"y":16},{"x":122,"y":16},{"x":123,"y":16},{"x":124,"y":16},{"x":125,"y":16},{"x":156,"y":16},{"x":157,"y":16},{"x":158,"y":16},{"x":159,"y":16},{"x":48,"y":17},{"x":49,"y":17},{"x":50,"y":17},{"x":51,"y":17},{"x":52,"y":17},{"x":53,"y":17},{"x":54,"y":17},{"x":55,"y":17},{"x":56,"y":17},{"x":57,"y":17},{"x":58,"y":17},{"x":59,"y":17},{"x":60,"y":17},{"x":61,"y":17},{"x":62,"y":17},{"x":63,"y":17},{"x":64,"y":17},{"x":65,"y":17},{"x":66,"y":17},{"x":67,"y":17},{"x":68,"y":17},{"x":69,"y":17},{"x":70,"y":17},{"x":71,"y":17},{"x":72,"y":17},{"x":73,"y":17},{"x":74,"y":17},{"x":75,"y":17},{"x":76,"y":17},{"x":85,"y":17},{"x":86,"y":17},{"x":87,"y":17},{"x":88,"y":17},{"x":89,"y":17},{"x":90,"y":17},{"x":91,"y":17},{"x":92,"y":17},{"x":93,"y":17},{"x":94,"y":17},{"x":95,"y":17},{"x":96,"y":17},{"x":97,"y":17},{"x":98,"y":17},{"x":104,"y":17},{"x":105,"y":17},{"x":106,"y":17},{"x":107,"y":17},{"x":109,"y":17},{"x":110,"y":17},{"x":112,"y":17},{"x":113,"y":17},{"x":115,"y":17},{"x":116,"y":17},{"x":118,"y":17},{"x":119,"y":17},{"x":121,"y":17},{"x":122,"y":17},{"x":123,"y":17},{"x":124,"y":17},{"x":125,"y":17},{"x":126,"y":17},{"x":155,"y":17},{"x":156,"y":17},{"x":157,"y":17},{"x":158,"y":17},{"x":159,"y":17},{"x":51,"y":18},{"x":52,"y":18},{"x":53,"y":18},{"x":58,"y":18},{"x":59,"y":18},{"x":60,"y":18},{"x":61,"y":18},{"x":62,"y":18},{"x":63,"y":18},{"x":64,"y":18},{"x":65,"y":18},{"x":66,"y":18},{"x":67,"y":18},{"x":68,"y":18},{"x":69,"y":18},{"x":70,"y":18},{"x":71,"y":18},{"x":72,"y":18},{"x":73,"y":18},{"x":74,"y":18},{"x":75,"y":18},{"x":76,"y":18},{"x":77,"y":18},{"x":78,"y":18},{"x":79,"y":18},{"x":80,"y":18},{"x":81,"y":18},{"x":82,"y":18},{"x":83,"y":18},{"x":84,"y":18},{"x":85,"y":18},{"x":86,"y":18},{"x":87,"y":18},{"x":88,"y":18},{"x":89,"y":18},{"x":90,"y":18},{"x":91,"y":18},{"x":92,"y":18},{"x":93,"y":18},{"x":94,"y":18},{"x":95,"y":18},{"x":96,"y":18},{"x":97,"y":18},{"x":98,"y":18},{"x":105,"y":18},{"x":106,"y":18},{"x":107,"y":18},{"x":109,"y":18},{"x":110,"y":18},{"x":112,"y":18},{"x":113,"y":18},{"x":115,"y":18},{"x":116,"y":18},{"x":118,"y":18},{"x":119,"y":18},{"x":121,"y":18},{"x":122,"y":18},{"x":123,"y":18},{"x":124,"y":18},{"x":152,"y":18},{"x":153,"y":18},{"x":154,"y":18},{"x":155,"y":18},{"x":156,"y":18},{"x":157,"y":18},{"x":158,"y":18},{"x":61,"y":19},{"x":62,"y":19},{"x":66,"y":19},{"x":67,"y":19},{"x":68,"y":19},{"x":69,"y":19},{"x":70,"y":19},{"x":71,"y":19},{"x":72,"y":19},{"x":73,"y":19},{"x":74,"y":19},{"x":75,"y":19},{"x":76,"y":19},{"x":77,"y":19},{"x":78,"y":19},{"x":79,"y":19},{"x":80,"y":19},{"x":81,"y":19},{"x":82,"y":19},{"x":83,"y":19},{"x":84,"y":19},{"x":85,"y":19},{"x":86,"y":19},{"x":87,"y":19},{"x":88,"y":19},{"x":89,"y":19},{"x":90,"y":19},{"x":91,"y":19},{"x":92,"y":19},{"x":93,"y":19},{"x":94,"y":19},{"x":95,"y":19},{"x":96,"y":19},{"x":97,"y":19},{"x":98,"y":19},{"x":106,"y":19},{"x":107,"y":19},{"x":109,"y":19},{"x":110,"y":19},{"x":111,"y":19},{"x":112,"y":19},{"x":113,"y":19},{"x":114,"y":19},{"x":115,"y":19},{"x":116,"y":19},{"x":117,"y":19},{"x":118,"y":19},{"x":119,"y":19},{"x":120,"y":19},{"x":121,"y":19},{"x":122,"y":19},{"x":123,"y":19},{"x":124,"y":19},{"x":138,"y":19},{"x":139,"y":19},{"x":140,"y":19},{"x":141,"y":19},{"x":142,"y":19},{"x":143,"y":19},{"x":144,"y":19},{"x":145,"y":19},{"x":146,"y":19},{"x":147,"y":19},{"x":148,"y":19},{"x":149,"y":19},{"x":150,"y":19},{"x":151,"y":19},{"x":152,"y":19},{"x":153,"y":19},{"x":154,"y":19},{"x":155,"y":19},{"x":156,"y":19},{"x":157,"y":19},{"x":72,"y":20},{"x":73,"y":20},{"x":74,"y":20},{"x":75,"y":20},{"x":76,"y":20},{"x":77,"y":20},{"x":78,"y":20},{"x":79,"y":20},{"x":80,"y":20},{"x":81,"y":20},{"x":82,"y":20},{"x":83,"y":20},{"x":84,"y":20},{"x":85,"y":20},{"x":87,"y":20},{"x":88,"y":20},{"x":89,"y":20},{"x":90,"y":20},{"x":91,"y":20},{"x":92,"y":20},{"x":93,"y":20},{"x":94,"y":20},{"x":95,"y":20},{"x":96,"y":20},{"x":97,"y":20},{"x":98,"y":20},{"x":99,"y":20},{"x":100,"y":20},{"x":106,"y":20},{"x":107,"y":20},{"x":109,"y":20},{"x":110,"y":20},{"x":111,"y":20},{"x":112,"y":20},{"x":113,"y":20},{"x":114,"y":20},{"x":115,"y":20},{"x":116,"y":20},{"x":117,"y":20},{"x":118,"y":20},{"x":119,"y":20},{"x":120,"y":20},{"x":121,"y":20},{"x":122,"y":20},{"x":123,"y":20},{"x":124,"y":20},{"x":134,"y":20},{"x":135,"y":20},{"x":136,"y":20},{"x":137,"y":20},{"x":138,"y":20},{"x":139,"y":20},{"x":140,"y":20},{"x":141,"y":20},{"x":142,"y":20},{"x":143,"y":20},{"x":144,"y":20},{"x":145,"y":20},{"x":146,"y":20},{"x":147,"y":20},{"x":148,"y":20},{"x":149,"y":20},{"x":150,"y":20},{"x":151,"y":20},{"x":152,"y":20},{"x":153,"y":20},{"x":154,"y":20},{"x":155,"y":20},{"x":156,"y":20},{"x":157,"y":20},{"x":92,"y":21},{"x":93,"y":21},{"x":94,"y":21},{"x":95,"y":21},{"x":96,"y":21},{"x":97,"y":21},{"x":98,"y":21},{"x":99,"y":21},{"x":100,"y":21},{"x":101,"y":21},{"x":102,"y":21},{"x":109,"y":21},{"x":110,"y":21},{"x":111,"y":21},{"x":112,"y":21},{"x":113,"y":21},{"x":114,"y":21},{"x":115,"y":21},{"x":116,"y":21},{"x":117,"y":21},{"x":118,"y":21},{"x":119,"y":21},{"x":120,"y":21},{"x":121,"y":21},{"x":122,"y":21},{"x":123,"y":21},{"x":124,"y":21},{"x":131,"y":21},{"x":132,"y":21},{"x":133,"y":21},{"x":134,"y":21},{"x":135,"y":21},{"x":136,"y":21},{"x":137,"y":21},{"x":138,"y":21},{"x":139,"y":21},{"x":140,"y":21},{"x":141,"y":21},{"x":142,"y":21},{"x":143,"y":21},{"x":144,"y":21},{"x":145,"y":21},{"x":146,"y":21},{"x":147,"y":21},{"x":148,"y":21},{"x":149,"y":21},{"x":150,"y":21},{"x":151,"y":21},{"x":152,"y":21},{"x":153,"y":21},{"x":95,"y":22},{"x":96,"y":22},{"x":97,"y":22},{"x":98,"y":22},{"x":99,"y":22},{"x":100,"y":22},{"x":101,"y":22},{"x":102,"y":22},{"x":103,"y":22},{"x":104,"y":22},{"x":105,"y":22},{"x":109,"y":22},{"x":110,"y":22},{"x":111,"y":22},{"x":112,"y":22},{"x":113,"y":22},{"x":114,"y":22},{"x":115,"y":22},{"x":116,"y":22},{"x":117,"y":22},{"x":118,"y":22},{"x":119,"y":22},{"x":120,"y":22},{"x":121,"y":22},{"x":122,"y":22},{"x":123,"y":22},{"x":124,"y":22},{"x":125,"y":22},{"x":126,"y":22},{"x":127,"y":22},{"x":128,"y":22},{"x":129,"y":22},{"x":130,"y":22},{"x":131,"y":22},{"x":132,"y":22},{"x":133,"y":22},{"x":134,"y":22},{"x":135,"y":22},{"x":136,"y":22},{"x":137,"y":22},{"x":138,"y":22},{"x":139,"y":22},{"x":140,"y":22},{"x":141,"y":22},{"x":142,"y":22},{"x":143,"y":22},{"x":144,"y":22},{"x":145,"y":22},{"x":146,"y":22},{"x":147,"y":22},{"x":148,"y":22},{"x":149,"y":22},{"x":150,"y":22},{"x":151,"y":22},{"x":96,"y":23},{"x":97,"y":23},{"x":98,"y":23},{"x":99,"y":23},{"x":100,"y":23},{"x":101,"y":23},{"x":102,"y":23},{"x":103,"y":23},{"x":104,"y":23},{"x":105,"y":23},{"x":106,"y":23},{"x":107,"y":23},{"x":108,"y":23},{"x":109,"y":23},{"x":110,"y":23},{"x":111,"y":23},{"x":112,"y":23},{"x":113,"y":23},{"x":114,"y":23},{"x":115,"y":23},{"x":116,"y":23},{"x":117,"y":23},{"x":118,"y":23},{"x":119,"y":23},{"x":120,"y":23},{"x":121,"y":23},{"x":122,"y":23},{"x":123,"y":23},{"x":124,"y":23},{"x":125,"y":23},{"x":126,"y":23},{"x":127,"y":23},{"x":128,"y":23},{"x":129,"y":23},{"x":130,"y":23},{"x":131,"y":23},{"x":132,"y":23},{"x":133,"y":23},{"x":134,"y":23},{"x":135,"y":23},{"x":136,"y":23},{"x":137,"y":23},{"x":138,"y":23},{"x":139,"y":23},{"x":140,"y":23},{"x":141,"y":23},{"x":142,"y":23},{"x":143,"y":23},{"x":144,"y":23},{"x":145,"y":23},{"x":146,"y":23},{"x":99,"y":24},{"x":100,"y":24},{"x":101,"y":24},{"x":102,"y":24},{"x":103,"y":24},{"x":104,"y":24},{"x":105,"y":24},{"x":106,"y":24},{"x":107,"y":24},{"x":108,"y":24},{"x":109,"y":24},{"x":110,"y":24},{"x":111,"y":24},{"x":112,"y":24},{"x":113,"y":24},{"x":114,"y":24},{"x":117,"y":24},{"x":118,"y":24},{"x":119,"y":24},{"x":120,"y":24},{"x":121,"y":24},{"x":122,"y":24},{"x":123,"y":24},{"x":124,"y":24},{"x":125,"y":24},{"x":126,"y":24},{"x":127,"y":24},{"x":128,"y":24},{"x":129,"y":24},{"x":130,"y":24},{"x":131,"y":24},{"x":132,"y":24},{"x":133,"y":24},{"x":134,"y":24},{"x":135,"y":24},{"x":136,"y":24},{"x":137,"y":24},{"x":138,"y":24},{"x":100,"y":25},{"x":101,"y":25},{"x":102,"y":25},{"x":103,"y":25},{"x":104,"y":25},{"x":105,"y":25},{"x":106,"y":25},{"x":107,"y":25},{"x":108,"y":25},{"x":109,"y":25},{"x":110,"y":25},{"x":111,"y":25},{"x":112,"y":25},{"x":118,"y":25},{"x":119,"y":25},{"x":120,"y":25},{"x":121,"y":25},{"x":122,"y":25},{"x":123,"y":25},{"x":124,"y":25},{"x":125,"y":25},{"x":126,"y":25},{"x":127,"y":25},{"x":128,"y":25},{"x":129,"y":25},{"x":130,"y":25},{"x":131,"y":25},{"x":134,"y":25},{"x":135,"y":25},{"x":136,"y":25},{"x":102,"y":26},{"x":103,"y":26},{"x":104,"y":26},{"x":105,"y":26},{"x":106,"y":26},{"x":107,"y":26},{"x":123,"y":26},{"x":124,"y":26},{"x":125,"y":26},{"x":126,"y":26},{"x":127,"y":26},{"x":128,"y":26}],"slimePos":{"x":-6.459999084472656,"y":-0.5050175189971924},"spiritPos":{"x":-4.484055519104004,"y":2.1479361057281496},"mapElements":[{"id":11,"pos":{"x":-15.5,"y":-2.5},"rot":0.0,"rev":false,"idLink":[]},{"id":5,"pos":{"x":-2.5,"y":-1.0},"rot":0.0,"rev":true,"idLink":[]},{"id":6,"pos":{"x":8.5,"y":-1.5},"rot":0.0,"rev":false,"idLink":[]},{"id":18,"pos":{"x":9.0,"y":3.5},"rot":90.0,"rev":false,"idLink":[]},{"id":10,"pos":{"x":11.5,"y":0.5},"rot":0.0,"rev":false,"idLink":[]},{"id":10,"pos":{"x":11.5,"y":1.5},"rot":0.0,"rev":false,"idLink":[]},{"id":7,"pos":{"x":14.5,"y":-2.0},"rot":0.0,"rev":false,"idLink":[8]},{"id":7,"pos":{"x":15.5,"y":-2.0},"rot":0.0,"rev":false,"idLink":[8]},{"id":4,"pos":{"x":18.0,"y":-2.0},"rot":0.0,"rev":false,"idLink":[]},{"id":15,"pos":{"x":19.5,"y":-2.0},"rot":0.0,"rev":false,"idLink":[]},{"id":16,"pos":{"x":22.0,"y":0.0},"rot":0.0,"rev":false,"idLink":[]},{"id":6,"pos":{"x":28.0,"y":8.0},"rot":0.0,"rev":false,"idLink":[]},{"id":7,"pos":{"x":28.0,"y":-1.0},"rot":0.0,"rev":false,"idLink":[14]},{"id":7,"pos":{"x":29.0,"y":-1.0},"rot":0.0,"rev":false,"idLink":[14]},{"id":4,"pos":{"x":32.5,"y":1.0},"rot":0.0,"rev":true,"idLink":[]},{"id":6,"pos":{"x":35.5,"y":8.5},"rot":0.0,"rev":false,"idLink":[]},{"id":8,"pos":{"x":35.5,"y":10.5},"rot":0.0,"rev":false,"idLink":[17]},{"id":1,"pos":{"x":35.5,"y":6.0},"rot":0.0,"rev":false,"idLink":[]},{"id":4,"pos":{"x":37.5,"y":0.0},"rot":0.0,"rev":false,"idLink":[]},{"id":7,"pos":{"x":38.0,"y":5.0},"rot":0.0,"rev":false,"idLink":[18,23]},{"id":16,"pos":{"x":40.5,"y":1.5},"rot":0.0,"rev":false,"idLink":[]},{"id":24,"pos":{"x":41.5,"y":1.0},"rot":0.0,"rev":false,"idLink":[]},{"id":24,"pos":{"x":42.5,"y":1.0},"rot":0.0,"rev":false,"idLink":[]},{"id":4,"pos":{"x":45.5,"y":4.0},"rot":0.0,"rev":true,"idLink":[]},{"id":1,"pos":{"x":46.5,"y":10.5},"rot":0.0,"rev":false,"idLink":[]},{"id":7,"pos":{"x":48.0,"y":5.0},"rot":0.0,"rev":false,"idLink":[24,26]},{"id":4,"pos":{"x":51.0,"y":6.0},"rot":0.0,"rev":true,"idLink":[]},{"id":16,"pos":{"x":60.5,"y":3.5},"rot":0.0,"rev":false,"idLink":[]},{"id":16,"pos":{"x":60.5,"y":5.0},"rot":0.0,"rev":false,"idLink":[]},{"id":16,"pos":{"x":60.5,"y":6.5},"rot":0.0,"rev":false,"idLink":[]},{"id":17,"pos":{"x":61.0,"y":10.0},"rot":0.0,"rev":false,"idLink":[]},{"id":16,"pos":{"x":61.5,"y":2.5},"rot":0.0,"rev":false,"idLink":[]},{"id":16,"pos":{"x":62.5,"y":1.5},"rot":0.0,"rev":false,"idLink":[]},{"id":16,"pos":{"x":63.5,"y":0.5},"rot":0.0,"rev":false,"idLink":[]},{"id":24,"pos":{"x":64.5,"y":0.0},"rot":0.0,"rev":false,"idLink":[]},{"id":15,"pos":{"x":65.0,"y":8.5},"rot":90.0,"rev":false,"idLink":[]},{"id":15,"pos":{"x":65.0,"y":7.5},"rot":90.0,"rev":false,"idLink":[]},{"id":15,"pos":{"x":65.0,"y":6.5},"rot":90.0,"rev":false,"idLink":[]},{"id":24,"pos":{"x":65.5,"y":5.0},"rot":180.0,"rev":false,"idLink":[]},{"id":24,"pos":{"x":65.5,"y":0.0},"rot":0.0,"rev":false,"idLink":[]},{"id":24,"pos":{"x":66.5,"y":5.0},"rot":180.0,"rev":false,"idLink":[]},{"id":24,"pos":{"x":66.5,"y":0.0},"rot":0.0,"rev":false,"idLink":[]},{"id":6,"pos":{"x":67.0,"y":-1.0},"rot":0.0,"rev":false,"idLink":[]},{"id":24,"pos":{"x":67.5,"y":5.0},"rot":180.0,"rev":false,"idLink":[]},{"id":24,"pos":{"x":67.5,"y":0.0},"rot":0.0,"rev":false,"idLink":[]},{"id":24,"pos":{"x":68.5,"y":5.0},"rot":180.0,"rev":false,"idLink":[]},{"id":24,"pos":{"x":68.5,"y":0.0},"rot":0.0,"rev":false,"idLink":[]},{"id":11,"pos":{"x":69.5,"y":8.5},"rot":0.0,"rev":false,"idLink":[]},{"id":24,"pos":{"x":69.5,"y":5.0},"rot":180.0,"rev":false,"idLink":[]},{"id":6,"pos":{"x":69.5,"y":6.5},"rot":0.0,"rev":false,"idLink":[]},{"id":24,"pos":{"x":69.5,"y":0.0},"rot":0.0,"rev":false,"idLink":[]},{"id":24,"pos":{"x":70.5,"y":5.0},"rot":180.0,"rev":false,"idLink":[]},{"id":24,"pos":{"x":70.5,"y":0.0},"rot":0.0,"rev":false,"idLink":[]},{"id":24,"pos":{"x":71.5,"y":5.0},"rot":180.0,"rev":false,"idLink":[]},{"id":24,"pos":{"x":71.5,"y":0.0},"rot":0.0,"rev":false,"idLink":[]},{"id":24,"pos":{"x":72.5,"y":5.0},"rot":180.0,"rev":false,"idLink":[]},{"id":24,"pos":{"x":72.5,"y":0.0},"rot":0.0,"rev":false,"idLink":[]},{"id":24,"pos":{"x":73.5,"y":5.0},"rot":180.0,"rev":false,"idLink":[]},{"id":24,"pos":{"x":73.5,"y":0.0},"rot":0.0,"rev":false,"idLink":[]},{"id":24,"pos":{"x":74.5,"y":0.0},"rot":0.0,"rev":false,"idLink":[]},{"id":24,"pos":{"x":74.5,"y":5.0},"rot":180.0,"rev":false,"idLink":[]},{"id":6,"pos":{"x":75.0,"y":-1.0},"rot":0.0,"rev":false,"idLink":[]},{"id":24,"pos":{"x":75.5,"y":0.0},"rot":0.0,"rev":false,"idLink":[]},{"id":24,"pos":{"x":75.5,"y":5.0},"rot":180.0,"rev":false,"idLink":[]},{"id":24,"pos":{"x":76.5,"y":5.0},"rot":180.0,"rev":false,"idLink":[]},{"id":24,"pos":{"x":76.5,"y":0.0},"rot":0.0,"rev":false,"idLink":[]},{"id":24,"pos":{"x":77.5,"y":5.0},"rot":180.0,"rev":false,"idLink":[]},{"id":24,"pos":{"x":77.5,"y":0.0},"rot":0.0,"rev":false,"idLink":[]},{"id":24,"pos":{"x":78.5,"y":5.0},"rot":180.0,"rev":false,"idLink":[]},{"id":24,"pos":{"x":78.5,"y":0.0},"rot":0.0,"rev":false,"idLink":[]},{"id":6,"pos":{"x":79.0,"y":7.5},"rot":0.0,"rev":false,"idLink":[]},{"id":24,"pos":{"x":79.5,"y":5.0},"rot":180.0,"rev":false,"idLink":[]},{"id":24,"pos":{"x":79.5,"y":0.0},"rot":0.0,"rev":false,"idLink":[]},{"id":24,"pos":{"x":80.5,"y":5.0},"rot":180.0,"rev":false,"idLink":[]},{"id":24,"pos":{"x":80.5,"y":0.0},"rot":0.0,"rev":false,"idLink":[]},{"id":24,"pos":{"x":81.5,"y":5.0},"rot":180.0,"rev":false,"idLink":[]},{"id":24,"pos":{"x":81.5,"y":0.0},"rot":0.0,"rev":false,"idLink":[]},{"id":24,"pos":{"x":81.5,"y":0.0},"rot":0.0,"rev":false,"idLink":[]},{"id":24,"pos":{"x":82.5,"y":5.0},"rot":180.0,"rev":false,"idLink":[]},{"id":24,"pos":{"x":82.5,"y":0.0},"rot":0.0,"rev":false,"idLink":[]},{"id":24,"pos":{"x":83.5,"y":5.0},"rot":180.0,"rev":false,"idLink":[]},{"id":24,"pos":{"x":83.5,"y":0.0},"rot":0.0,"rev":false,"idLink":[]},{"id":24,"pos":{"x":84.5,"y":5.0},"rot":180.0,"rev":false,"idLink":[]},{"id":24,"pos":{"x":84.5,"y":0.0},"rot":0.0,"rev":false,"idLink":[]},{"id":24,"pos":{"x":85.5,"y":0.0},"rot":0.0,"rev":false,"idLink":[]},{"id":24,"pos":{"x":85.5,"y":5.0},"rot":180.0,"rev":false,"idLink":[]},{"id":24,"pos":{"x":86.5,"y":0.0},"rot":0.0,"rev":false,"idLink":[]},{"id":24,"pos":{"x":86.5,"y":5.0},"rot":180.0,"rev":false,"idLink":[]},{"id":24,"pos":{"x":87.5,"y":0.0},"rot":0.0,"rev":false,"idLink":[]},{"id":24,"pos":{"x":88.5,"y":0.0},"rot":0.0,"rev":false,"idLink":[]},{"id":24,"pos":{"x":89.5,"y":0.0},"rot":0.0,"rev":false,"idLink":[]},{"id":22,"pos":{"x":92.0,"y":10.0},"rot":0.0,"rev":false,"idLink":[]},{"id":17,"pos":{"x":96.0,"y":16.0},"rot":180.0,"rev":true,"idLink":[]},{"id":7,"pos":{"x":109.0,"y":-15.0},"rot":0.0,"rev":false,"idLink":[101]},{"id":23,"pos":{"x":109.0,"y":-0.5},"rot":0.0,"rev":false,"idLink":[]},{"id":0,"pos":{"x":109.0,"y":0.5},"rot":-0.0008427175343967974,"rev":false,"idLink":[]},{"id":4,"pos":{"x":110.5,"y":7.0},"rot":0.0,"rev":false,"idLink":[]},{"id":23,"pos":{"x":111.5,"y":16.5},"rot":0.0,"rev":false,"idLink":[]},{"id":23,"pos":{"x":111.5,"y":11.5},"rot":0.0,"rev":false,"idLink":[]},{"id":13,"pos":{"x":111.5,"y":17.5},"rot":0.0,"rev":false,"idLink":[]},{"id":7,"pos":{"x":112.0,"y":-15.0},"rot":0.0,"rev":false,"idLink":[107,103,104]},{"id":23,"pos":{"x":112.0,"y":-0.5},"rot":0.0,"rev":false,"idLink":[]},{"id":0,"pos":{"x":112.0,"y":0.5},"rot":-0.0008426575222983956,"rev":false,"idLink":[]},{"id":23,"pos":{"x":114.5,"y":16.5},"rot":0.0,"rev":false,"idLink":[]},{"id":23,"pos":{"x":114.5,"y":11.5},"rot":0.0,"rev":false,"idLink":[]},{"id":13,"pos":{"x":114.5,"y":17.5},"rot":0.0,"rev":false,"idLink":[]},{"id":7,"pos":{"x":115.0,"y":-15.0},"rot":0.0,"rev":false,"idLink":[115]},{"id":23,"pos":{"x":115.0,"y":-0.5},"rot":0.0,"rev":false,"idLink":[]},{"id":0,"pos":{"x":115.0,"y":0.5},"rot":-0.0008424398838542402,"rev":false,"idLink":[]},{"id":6,"pos":{"x":116.0,"y":5.5},"rot":0.0,"rev":false,"idLink":[]},{"id":8,"pos":{"x":116.0,"y":9.5},"rot":0.0,"rev":false,"idLink":[96,123,94,97,98]},{"id":23,"pos":{"x":117.5,"y":11.5},"rot":0.0,"rev":false,"idLink":[]},{"id":23,"pos":{"x":117.5,"y":16.5},"rot":0.0,"rev":false,"idLink":[]},{"id":13,"pos":{"x":117.5,"y":17.5},"rot":0.0,"rev":false,"idLink":[]},{"id":7,"pos":{"x":118.0,"y":-15.0},"rot":0.0,"rev":false,"idLink":[121,112,111]},{"id":23,"pos":{"x":118.0,"y":-0.5},"rot":0.0,"rev":false,"idLink":[]},{"id":0,"pos":{"x":118.0,"y":0.5},"rot":-0.0008425849955528975,"rev":false,"idLink":[]},{"id":0,"pos":{"x":120.5,"y":17.5},"rot":0.013000644743442536,"rev":false,"idLink":[]},{"id":23,"pos":{"x":120.5,"y":11.5},"rot":0.0,"rev":false,"idLink":[]},{"id":23,"pos":{"x":120.5,"y":16.5},"rot":0.0,"rev":false,"idLink":[]},{"id":7,"pos":{"x":121.0,"y":-15.0},"rot":0.0,"rev":false,"idLink":[125]},{"id":23,"pos":{"x":121.0,"y":-0.5},"rot":0.0,"rev":false,"idLink":[]},{"id":0,"pos":{"x":121.0,"y":0.5},"rot":-0.0008425983251072466,"rev":false,"idLink":[]},{"id":4,"pos":{"x":121.5,"y":7.0},"rot":0.0,"rev":true,"idLink":[]},{"id":7,"pos":{"x":124.0,"y":-15.0},"rot":0.0,"rev":false,"idLink":[119,118]},{"id":23,"pos":{"x":124.0,"y":-0.5},"rot":0.0,"rev":false,"idLink":[]},{"id":0,"pos":{"x":124.0,"y":0.5},"rot":-0.000841884408146143,"rev":false,"idLink":[]},{"id":11,"pos":{"x":125.5,"y":18.5},"rot":0.0,"rev":false,"idLink":[]},{"id":15,"pos":{"x":131.5,"y":7.0},"rot":0.0,"rev":false,"idLink":[]},{"id":14,"pos":{"x":132.5,"y":12.5},"rot":0.0,"rev":false,"idLink":[]},{"id":15,"pos":{"x":133.5,"y":7.0},"rot":0.0,"rev":false,"idLink":[]},{"id":14,"pos":{"x":135.5,"y":13.5},"rot":0.0,"rev":false,"idLink":[]},{"id":6,"pos":{"x":137.5,"y":10.0},"rot":0.0,"rev":false,"idLink":[]},{"id":15,"pos":{"x":137.5,"y":6.0},"rot":0.0,"rev":false,"idLink":[]},{"id":15,"pos":{"x":138.5,"y":6.0},"rot":0.0,"rev":false,"idLink":[]},{"id":5,"pos":{"x":151.5,"y":11.0},"rot":0.0,"rev":false,"idLink":[]},{"id":12,"pos":{"x":154.0,"y":12.0},"rot":0.0,"rev":false,"idLink":[]},{"id":5,"pos":{"x":156.5,"y":11.0},"rot":0.0,"rev":true,"idLink":[]}]}